serums/__init__.py
serums/distances.py
serums/distribution_estimator.py
serums/distribution_overbounder.py
serums/enums.py
serums/error_processor.py
serums/errors.py
serums/models.py
serums-1.0.6.dist-info/LICENSE
serums-1.0.6.dist-info/METADATA
serums-1.0.6.dist-info/WHEEL
serums-1.0.6.dist-info/top_level.txt
serums-1.0.6.dist-info/RECORD
