Metadata-Version: 2.1
Name: serums
Version: 1.0.6
Summary: A Python package for Statistical Error and Risk Utility for Multi-sensor Systems (SERUMS).
Author: Laboratory for Autonomy GNC and Estimation Research (LAGER)
License: MIT License
Project-URL: homepage, http://lager.ua.edu/
Project-URL: documentation, https://drjdlarson.github.io/serums/
Project-URL: repository, https://github.com/drjdlarson/serums
Keywords: Statistical error,overbounding,Gaussian distributions,multi-sensor systems
Classifier: Intended Audience :: Developers
Classifier: Intended Audience :: Education
Classifier: Intended Audience :: Science/Research
Classifier: Programming Language :: Python
Classifier: Programming Language :: Python :: 3.7
Classifier: Programming Language :: Python :: 3.8
Classifier: Programming Language :: Python :: 3.9
Classifier: Topic :: Scientific/Engineering
Requires-Python: >=3.7
License-File: LICENSE
Requires-Dist: numpy
Requires-Dist: scipy
Requires-Dist: matplotlib
Requires-Dist: probscale
Requires-Dist: pandas
